commit_critic/__init__.py
commit_critic/commit_critic.py
commit_critic-0.1.dist-info/METADATA
commit_critic-0.1.dist-info/WHEEL
commit_critic-0.1.dist-info/entry_points.txt
commit_critic-0.1.dist-info/RECORD
