Metadata-Version: 2.3
Name: commit-critic
Version: 0.1
Summary: Command line tool for generating code review prompts using the Metaphor format
Project-URL: Homepage, https://github.com/m6r-ai/commit-critic
Project-URL: Issues, https://github.com/m6r-ai/commit-critic/issues
Author-email: M6R <hello@m6r.ai>
Classifier: License :: OSI Approved :: Apache Software License
Classifier: Operating System :: OS Independent
Classifier: Programming Language :: Python :: 3
Requires-Python: >=3.8
Requires-Dist: m6rclib>=0.3.0
